[
  {
    "id": "3d59eab5-2c19-4650-95ba-25e90bd5e0fd",
    "title": "Choose correct answer of   S + V.",
    "answer1": "Present simple",
    "answer2": "Present continue",
    "answer3": "Present perfect",
    "answer4": "past simple ",
    "score": 10,
    "correctAnswer": "A"
  },
  {
    "id": "15132274-1e30-4db9-a6df-048be605bd60",
    "title": "I  ---------(not/study) in this morning.",
    "answer1": "I am not work in this morning.",
    "answer2": "I don't work in this morning.",
    "answer3": "I not work in this morning.",
    "answer4": "I doesn't work in this morning.",
    "score": 10,
    "correctAnswer": "B"
  },
  {
    "id": "e94da08c-8faa-44d0-81aa-fac521647d9b",
    "title": "I ------------ a student.",
    "answer1": "I am a student.",
    "answer2": "I does a student.",
    "answer3": "I am an student.",
    "answer4": "I am a students.",
    "score": 10,
    "correctAnswer": "A"
  },
  {
    "id": "2db4cad1-d893-4a00-a599-a62318229ef2",
    "title": "He and you ---------- teachers.",
    "answer1": "He and you is a teachers.",
    "answer2": "He and you are a teachers.",
    "answer3": "He and you are teachers.",
    "answer4": "He and you are teacher.",
    "score": 10,
    "correctAnswer": "C"
  },
  {
    "id": "8914e30d-bd35-4b21-bd21-cd356766ec5b",
    "title": "------ you like this computer?",
    "answer1": "Does you like this computer?",
    "answer2": "Do you likes this computer?",
    "answer3": "Does you likes this computer?",
    "answer4": "Do you like this computer?",
    "score": 10,
    "correctAnswer": "D"
  }
]